.gitignore
CHANGES.rst
LICENSE.txt
MANIFEST.in
README.rst
bootstrap.py
buildout.cfg
setup.py
js/__init__.py
js.jquery_jcrop.egg-info/PKG-INFO
js.jquery_jcrop.egg-info/SOURCES.txt
js.jquery_jcrop.egg-info/dependency_links.txt
js.jquery_jcrop.egg-info/entry_points.txt
js.jquery_jcrop.egg-info/namespace_packages.txt
js.jquery_jcrop.egg-info/not-zip-safe
js.jquery_jcrop.egg-info/requires.txt
js.jquery_jcrop.egg-info/top_level.txt
js/jquery_jcrop/__init__.py
js/jquery_jcrop/test_jcrop.txt
js/jquery_jcrop/resources/Jcrop.gif
js/jquery_jcrop/resources/jquery.Jcrop.css
js/jquery_jcrop/resources/jquery.Jcrop.js
js/jquery_jcrop/resources/jquery.Jcrop.min.css
js/jquery_jcrop/resources/jquery.Jcrop.min.js
js/jquery_jcrop/resources/jquery.color.js