Metadata-Version: 1.0
Name: js.jquery-jcrop
Version: 0.9.10
Summary: Fanstatic packaging of jCrop
Home-page: UNKNOWN
Author: Fanstatic Developers
Author-email: fanstatic@googlegroups.com
License: BSD
Platform: UNKNOWN
